adafruit_st7735.py
adafruit_circuitpython_st7735-1.2.20.dist-info/licenses/LICENSE
adafruit_circuitpython_st7735-1.2.20.dist-info/METADATA
adafruit_circuitpython_st7735-1.2.20.dist-info/WHEEL
adafruit_circuitpython_st7735-1.2.20.dist-info/top_level.txt
adafruit_circuitpython_st7735-1.2.20.dist-info/RECORD
